<?xml version="1.0" encoding="utf-8" ?><dwsync><file name="footer.php" server="ftp.discobuzz.com.au/public_html/sunshinemensclothing.website/" local="3515467450" remote="318763443908356812" Dst="-1" /><file name="footer.php" server="OS/Applications/XAMPP/xamppfiles/htdocs/hanselandpetal/" local="3515467450" remote="318763443908363962" Dst="-1" /><file name="db_connect.php" server="spider.science.mq.edu.au//NewStar/" local="3524133875" remote="318763443917419332" Dst="-1" /><file name="footer.php" server="spider.science.mq.edu.au//NewStar/" local="3523924444" remote="318763443917419332" Dst="-1" /><file name="functions2.php" server="spider.science.mq.edu.au//NewStar/" local="3524137795" remote="318763443917419332" Dst="-1" /><file name="getUserInfo.php" server="spider.science.mq.edu.au//NewStar/" local="3524137291" remote="318763443917419332" Dst="-1" /><file name="HeadScrips.php" server="spider.science.mq.edu.au//NewStar/" local="3523352570" remote="318763443917419332" Dst="-1" /><file name="logout.php" server="spider.science.mq.edu.au//NewStar/" local="3524133877" remote="318763443917419332" Dst="-1" /><file name="pagetop.php" server="spider.science.mq.edu.au//NewStar/" local="3524139242" remote="318763443917419332" Dst="-1" /><file name="process_login.php" server="spider.science.mq.edu.au//NewStar/" local="3524133875" remote="318763443917419332" Dst="-1" /><file name="protectedPageBegin.php" server="spider.science.mq.edu.au//NewStar/" local="3524133875" remote="318763443917419332" Dst="-1" /><file name="psl-config.php" server="spider.science.mq.edu.au//NewStar/" local="3523338521" remote="318763443917419332" Dst="-1" /><file name="register.inc3.php" server="spider.science.mq.edu.au//NewStar/" local="3524522341" remote="318763443917419332" Dst="-1" /><file name="db_connect.php" server="ftp.discobuzz.com.au//public_html/comp344Ass2_PDO/" local="3528022759" remote="3528013800" Dst="-1" /><file name="db_connect_PDO.php" server="ftp.discobuzz.com.au//public_html/comp344Ass2_PDO/" local="3528024138" remote="3528016500" Dst="-1" /><file name="getUserInfo.php" server="ftp.discobuzz.com.au//public_html/comp344Ass2_PDO/" local="3528022759" remote="3528013800" Dst="-1" /><file name="footer.php" server="ftp.discobuzz.com.au//public_html/comp344Ass2_PDO/" local="3528022759" remote="3528013800" Dst="-1" /><file name="functions2.php" server="ftp.discobuzz.com.au//public_html/comp344Ass2_PDO/" local="3528023127" remote="3528013800" Dst="-1" /><file name="HeadScrips.php" server="ftp.discobuzz.com.au//public_html/comp344Ass2_PDO/" local="3528022759" remote="3528013800" Dst="-1" /><file name="pagetop.php" server="ftp.discobuzz.com.au//public_html/comp344Ass2_PDO/" local="3528027122" remote="3528016320" Dst="-1" /><file name="logout.php" server="ftp.discobuzz.com.au//public_html/comp344Ass2_PDO/" local="3528022759" remote="3528013800" Dst="-1" /><file name="process_login.php" server="ftp.discobuzz.com.au//public_html/comp344Ass2_PDO/" local="3528022759" remote="3528013800" Dst="-1" /><file name="protectedPageBegin.php" server="ftp.discobuzz.com.au//public_html/comp344Ass2_PDO/" local="3528022759" remote="3528013800" Dst="-1" /><file name="psl-config.php" server="ftp.discobuzz.com.au//public_html/comp344Ass2_PDO/" local="3528022759" remote="3528013800" Dst="-1" /><file name="register.inc3.php" server="ftp.discobuzz.com.au//public_html/comp344Ass2_PDO/" local="3528022759" remote="3528013800" Dst="-1" /></dwsync>